{
    "meta": {
        "title": "Ice Cream",
        "defaultLanguage": "Korean"
    },
    "aboutMe": {
        "name": "윤태인",
        "nickName": "Ice Cream",
        "profileImg": "../assets/images/emoji-unscreen.gif",
        "email": "icecream2370@kakao.com",
        "githubUrl": "https://github.com/icecream0910",
        "blogUrl": "https://taein0910.github.io/blog",
        "linkedInUrl": ""
    },

    "skillSets": [{
            "category": "Front End Skills",
            "skills": [
                { "skill": "Javascript", "level": "5" },
                { "skill": "HTML/CSS", "level": "5" },
                { "skill": "Android", "level": "4" }
            ]
        },
        {
            "category": "Back End Skills",
            "skills": [
                { "skill": "Node.js", "level": "4" },
                { "skill": "Java", "level": "4" },
                { "skill": "Spring", "level": "3" },
                { "skill": "Python", "level": "2" }

            ]
        },
        {
            "category": "Collaboration Skills",
            "skills": [
                { "skill": "Git/Github" },
                { "skill": "Notion" },
                { "skill": "채널톡" },
                { "skill": "Swit" }
            ]
        },
        {
            "category": "Etc...",
            "skills": [
                { "skill": "Heroku" },
                { "skill": "AWS EC2" },
                { "skill": "AWS Beanstalk" }
            ]
        }
    ],

    "projects": [{
            "imgUrl": "",
            "githubUrl": "https://github.com/ddongule",
            "projectUrl": "",
            "title": "[Team] Project Title",
            "term": "21.02.02 v1.3.0",
            "description": "About the project ... Lorem ipsum dolor sit amet consectetur adipisicing elit. Maxime mollitia ..",
            "attribution": "How you made it.. Technology that you used.. Lorem ipsum dolor sit amet consectetur adipisicing elit. Maxime mollitia ..",
            "tags": ["React", "Javascript", "Java", "Spring"]
        },
        {
            "imgUrl": "/assets/images/example-image-light.png",
            "githubUrl": "https://github.com/ddongule",
            "projectUrl": "",
            "title": "[Personal] Project Title",
            "term": "21.01.01 v1.0.0",
            "description": "About the project ... Lorem ipsum dolor sit amet consectetur adipisicing elit. Maxime mollitia ..",
            "attribution": "How you made it.. Technology that you used.. Lorem ipsum dolor sit amet consectetur adipisicing elit. Maxime mollitia ..",
            "tags": ["React", "Javascript", "Java", "Spring"]
        }
    ],

    "timestamp": [{
        "title": "고등학교 재학중",
        "when": "2021 ~ ",
        "organizer": "경기 성일고등학교",
        "tags": ["school"]
    }],

    "experiences": [],

    "educations": [{
            "title": "정보처리기능사",
            "term": "2017.12",
            "description": "한국산업인력공단"
        },
        {
            "title": "컴퓨터활용능력 2급",
            "term": "2016.12",
            "description": "대한상공회의소"
        },
        {
            "title": "GTQ(그래픽기술자격) 1급",
            "term": "2017.03",
            "description": "한국생산성본부"
        }
    ]
}